cloudstructs/__init__.py
cloudstructs/py.typed
cloudstructs/_jsii/__init__.py
cloudstructs/_jsii/cloudstructs@0.12.7.jsii.tgz
cloudstructs-0.12.7.dist-info/LICENSE
cloudstructs-0.12.7.dist-info/METADATA
cloudstructs-0.12.7.dist-info/WHEEL
cloudstructs-0.12.7.dist-info/top_level.txt
cloudstructs-0.12.7.dist-info/RECORD
